PythonAdvancedTyping/__init__.py
PythonAdvancedTyping/type_checking.py
python_advanced_typing-0.15.dist-info/LICENSE.md
python_advanced_typing-0.15.dist-info/METADATA
python_advanced_typing-0.15.dist-info/WHEEL
python_advanced_typing-0.15.dist-info/top_level.txt
python_advanced_typing-0.15.dist-info/RECORD
