Metadata-Version: 2.1
Name: python-advanced-typing
Version: 0.15
Summary: An intuitive Python utility to ensure type accuracy in your code. With capabilities to validate single or multiple variables, it streamlines type verification, boosting code reliability and readability.
Home-page: https://github.com/YidiSprei/PythonAdvancedTyping
Author: Yidi Sprei
Author-email: yididev@gmail.com
Classifier: Programming Language :: Python :: 3
Classifier: License :: OSI Approved :: MIT License
License-File: LICENSE.md
